alibabacloud_dyvmsapi20170525/__init__.py
alibabacloud_dyvmsapi20170525/client.py
alibabacloud_dyvmsapi20170525/models/__init__.py
alibabacloud_dyvmsapi20170525/models/_add_virtual_number_relation_request.py
alibabacloud_dyvmsapi20170525/models/_add_virtual_number_relation_response.py
alibabacloud_dyvmsapi20170525/models/_add_virtual_number_relation_response_body.py
alibabacloud_dyvmsapi20170525/models/_batch_robot_smart_call_request.py
alibabacloud_dyvmsapi20170525/models/_batch_robot_smart_call_response.py
alibabacloud_dyvmsapi20170525/models/_batch_robot_smart_call_response_body.py
alibabacloud_dyvmsapi20170525/models/_cancel_call_request.py
alibabacloud_dyvmsapi20170525/models/_cancel_call_response.py
alibabacloud_dyvmsapi20170525/models/_cancel_call_response_body.py
alibabacloud_dyvmsapi20170525/models/_cancel_order_robot_task_request.py
alibabacloud_dyvmsapi20170525/models/_cancel_order_robot_task_response.py
alibabacloud_dyvmsapi20170525/models/_cancel_order_robot_task_response_body.py
alibabacloud_dyvmsapi20170525/models/_cancel_robot_task_request.py
alibabacloud_dyvmsapi20170525/models/_cancel_robot_task_response.py
alibabacloud_dyvmsapi20170525/models/_cancel_robot_task_response_body.py
alibabacloud_dyvmsapi20170525/models/_change_media_type_request.py
alibabacloud_dyvmsapi20170525/models/_change_media_type_response.py
alibabacloud_dyvmsapi20170525/models/_change_media_type_response_body.py
alibabacloud_dyvmsapi20170525/models/_create_call_task_request.py
alibabacloud_dyvmsapi20170525/models/_create_call_task_response.py
alibabacloud_dyvmsapi20170525/models/_create_call_task_response_body.py
alibabacloud_dyvmsapi20170525/models/_create_robot_task_request.py
alibabacloud_dyvmsapi20170525/models/_create_robot_task_response.py
alibabacloud_dyvmsapi20170525/models/_create_robot_task_response_body.py
alibabacloud_dyvmsapi20170525/models/_degrade_video_file_request.py
alibabacloud_dyvmsapi20170525/models/_degrade_video_file_response.py
alibabacloud_dyvmsapi20170525-4.2.0.dist-info/LICENSE
alibabacloud_dyvmsapi20170525-4.2.0.dist-info/METADATA
alibabacloud_dyvmsapi20170525-4.2.0.dist-info/WHEEL
alibabacloud_dyvmsapi20170525-4.2.0.dist-info/top_level.txt
alibabacloud_dyvmsapi20170525-4.2.0.dist-info/RECORD
